crdt_tool_api_client/__init__.py
crdt_tool_api_client/api/__init__.py
crdt_tool_api_client/api/credit_products/__init__.py
crdt_tool_api_client/api/credit_products/credit_products_create.py
crdt_tool_api_client/api/credit_products/credit_products_destroy.py
crdt_tool_api_client/api/credit_products/credit_products_list.py
crdt_tool_api_client/api/credit_products/credit_products_partial_update.py
crdt_tool_api_client/api/credit_products/credit_products_retrieve.py
crdt_tool_api_client/api/credit_products/credit_products_update.py
crdt_tool_api_client/api/customers/__init__.py
crdt_tool_api_client/api/customers/customers_create.py
crdt_tool_api_client/api/customers/customers_destroy.py
crdt_tool_api_client/api/customers/customers_list.py
crdt_tool_api_client/api/customers/customers_partial_update.py
crdt_tool_api_client/api/customers/customers_retrieve.py
crdt_tool_api_client/api/customers/customers_update.py
crdt_tool_api_client/api/groups/__init__.py
crdt_tool_api_client/api/groups/groups_create.py
crdt_tool_api_client/api/groups/groups_destroy.py
crdt_tool_api_client/api/groups/groups_list.py
crdt_tool_api_client/api/groups/groups_partial_update.py
crdt_tool_api_client/api/groups/groups_retrieve.py
crdt_tool_api_client/api/groups/groups_update.py
crdt_tool_api_client/api/leads/__init__.py
crdt_tool_api_client/api/leads/leads_create.py
crdt_tool_api_client/api/leads/leads_destroy.py
crdt_tool_api_client/api/leads/leads_partial_update.py
crdt_tool_api_client/api/leads/leads_retrieve.py
crdt_tool_api_client/api/leads/leads_retrieve_2.py
crdt_tool_api_client/api/leads/leads_update.py
crdt_tool_api_client/api/login/__init__.py
crdt_tool_api_client/api/login/login_create.py
crdt_tool_api_client/api/permissions/__init__.py
crdt_tool_api_client/api/permissions/permissions_create.py
crdt_tool_api_client/api/permissions/permissions_destroy.py
crdt_tool_api_client/api/permissions/permissions_list.py
crdt_tool_api_client/api/permissions/permissions_partial_update.py
crdt_tool_api_client-1.0.3.dist-info/METADATA
crdt_tool_api_client-1.0.3.dist-info/WHEEL
crdt_tool_api_client-1.0.3.dist-info/RECORD
